LICENSE
MANIFEST.in
README.md
setup.cfg
setup.py
examples/__init__.py
examples/echobot.py
gyr/__init__.py
gyr/api.py
gyr/exceptions.py
gyr/matrix_objects.py
gyr/resources.py
gyr/server.py
gyr/utils.py
gyr.egg-info/PKG-INFO
gyr.egg-info/SOURCES.txt
gyr.egg-info/dependency_links.txt
gyr.egg-info/requires.txt
gyr.egg-info/top_level.txt