Metadata-Version: 1.1
Name: gyr
Version: 0.2.0
Summary: A python framework for building matrix application services
Home-page: https://github.com/non-Jedi/gyr
Author: Adam Beckmeyer
Author-email: adam_git@thebeckmeyers.xyz
License: GPLv3
Keywords: matrix chat falcon WSGI application-service
Platform: UNKNOWN
Classifier: Development Status :: 3 - Alpha
Classifier: Intended Audience :: Developers
Classifier: License :: OSI Approved :: GNU General Public License v3 (GPLv3)
Classifier: Topic :: Software Development :: Libraries :: Application Frameworks
Classifier: Topic :: Internet :: WWW/HTTP :: WSGI
Classifier: Topic :: Communications :: Chat
Classifier: Programming Language :: Python :: 3
